__init__.py
tiny_tui/App.py
tiny_tui/AppContext.py
tiny_tui/Global_exceptions.py
tiny_tui/__init__.py
tiny_tui/Menu/Menu.py
tiny_tui/Menu/Menu_Item.py
tiny_tui-0.0.1024.dist-info/licenses/LICENSE
tiny_tui-0.0.1024.dist-info/METADATA
tiny_tui-0.0.1024.dist-info/WHEEL
tiny_tui-0.0.1024.dist-info/top_level.txt
tiny_tui-0.0.1024.dist-info/RECORD
