Metadata-Version: 2.4
Name: tiny_tui
Version: 0.0.1024
Summary: Tiny package for fast implementing the simpliest tui on Python
Author-email: fakemade <u.s.selivanov@mail.ru>
License-Expression: MIT
Project-URL: Homepage, https://github.com/fakemade/tiny_tui
Project-URL: Issues, https://github.com/fakemade/tiny_tui/issues
Classifier: Programming Language :: Python :: 3
Classifier: Operating System :: OS Independent
Classifier: Development Status :: 3 - Alpha
Classifier: Environment :: Console
Requires-Python: >=3.9
License-File: LICENSE
Dynamic: license-file
